pyarcgenerator/__init__.py
pyarcgenerator/config.py
pyarcgenerator/exception.py
pyarcgenerator/gen.py
pyarcgenerator/gen_schema.py
pyarcgenerator/methods.py
pyarcgenerator-0.0.2.dist-info/METADATA
pyarcgenerator-0.0.2.dist-info/WHEEL
pyarcgenerator-0.0.2.dist-info/top_level.txt
pyarcgenerator-0.0.2.dist-info/RECORD
