Metadata-Version: 2.1
Name: pyarcgenerator
Version: 0.0.2
Summary: Package permettant de generer un ensemble de fichiers et de fichier en fonction de la configuration voulu.
Home-page: UNKNOWN
Author: INICODE
Author-email: contact.inicode@gmail.com
License: UNKNOWN
Keywords: python,hivi,pyarcgenerator,generator
Platform: UNKNOWN
Requires-Dist: pytz ; python_version >= "2022.1"
Requires-Dist: asyncio ; python_version >= "3.4.3"
Requires-Dist: typing ; python_version >= "3.7.4.3"
